[{"name":"中山市体育运动学校","address":"广东省中山市石岐区民权路23号","phone":"760-88826060","code":" 3644000564","nature":"中等技术学校"},{"name":"中山市中等专业学校","address":"广东省中山市五桂山丹桂路9号","phone":"760-88328419","code":" 3644000567","nature":"调整后中等职业学校"},{"name":"中山市火炬科学技术学校","address":"广东省中山市火炬开发区沿江东三路20号   中山市南朗镇体育路","phone":"760-28135903","code":" 3644000568","nature":"职业高中学校"},{"name":"中山市建斌职业技术学校","address":"广东省中山市小榄镇文东南街18号","phone":"760-22113672","code":" 3644000570","nature":"职业高中学校"},{"name":"中山市沙溪理工学校","address":"广东省中山市沙溪镇理工路13号","phone":"760-86238100","code":" 3644000574","nature":"职业高中学校"},{"name":"中山市第一职业技术学校","address":"中山市横栏镇景帝路16号","phone":"760-87766450","code":" 3644000577","nature":"职业高中学校"},{"name":"中山市现代职业技术学校","address":"广东省中山市三乡镇金涌大道23号","phone":"760-86337636","code":" 3644000580","nature":"职业高中学校"},{"name":"中山市南头华晖学校","address":"广东省中山市南头镇建设路62号","phone":"760-89733861","code":" 2144001741","nature":"小学"},{"name":"中山市西区铁城小学","address":"中山市西区翠景南路17号剑桥郡花园内","phone":"760-28136315","code":" 2144005404","nature":"小学"},{"name":"中山市西区广丰小学","address":"中山市西区广丰工业大道50号爱琴湾二期二区","phone":"760-88557501","code":" 2144006579","nature":"小学"},{"name":"中山火炬高技术产业开发区博凯小学","address":"中山市火炬开发区凯捷路20号","phone":"760-820565","code":" 2144008548","nature":"小学"},{"name":"中山市坦洲镇金斗湾小学","address":"中山市坦洲镇环洲北路9号","phone":"760-86288635","code":" 2144008850","nature":"小学"},{"name":"中山市南区马岭小学","address":"中山市南区马岭村福晟天地商住小区内","phone":"760-88897215","code":" 2144009151","nature":"小学"},{"name":"中山纪念小学","address":"广东省中山市翠亨新区集翠街2号","phone":"760-88286991","code":" 2144009992","nature":"小学"},{"name":"中山火炬高技术产业开发区第八小学","address":"广东省中山市火炬开发区依云路1号君华新城116号","phone":"760-23601386","code":" 2144010285","nature":"小学"},{"name":"中山火炬高技术产业开发区第九小学","address":"中山火炬开发区东镇东二路与小隐涌交汇处东北角地块1号","phone":"760-88589181","code":" 2144010753","nature":"小学"},{"name":"中山市小榄镇接龙小学","address":"广东省中山市小榄镇裕民社区接龙路37号接龙小学","phone":"86-2226536","code":" 2144010770","nature":"小学"},{"name":"中山市香山小学","address":"广东省中山市东区博爱七路8号","phone":"760-88826333","code":" 2144010968","nature":"小学"},{"name":"中山市坦洲镇阳光小学","address":"","phone":"760-86288903","code":" 2144011054","nature":"小学"},{"name":"中山市西区丰山学校","address":"","phone":"760-88668525","code":" 2144011994","nature":"小学"},{"name":"中山市坦洲镇同德小学","address":"","phone":"760-无","code":" 2144012005","nature":"小学"},{"name":"中山市岐江实验小学","address":"","phone":"760-88862211","code":" 2144012038","nature":"小学"},{"name":"中山市鸿瑞学校","address":"","phone":"760-88289319","code":" 2144012519","nature":"小学"},{"name":"中山市坦洲镇方德小学","address":"","phone":"760-86639189","code":" 2144012549","nature":"小学"},{"name":"中山市石岐高家基小学","address":"广东省中山市石岐区太平路高家基巷2号","phone":"760-88859160","code":" 2144016894","nature":"小学"},{"name":"中山市石岐区厚兴郑伟权学校","address":"广东省中山市石岐区厚兴兴业路22号","phone":"760-88704324","code":" 2144016895","nature":"小学"},{"name":"中山市石岐西厂小学","address":"中山市石岐区逢源路10号之一","phone":"760-88877783","code":" 2144016896","nature":"小学"},{"name":"中山市石岐区员峰小学","address":"广东省中山市石岐区员峰吉祥里1号","phone":"760-88704972","code":" 2144016897","nature":"小学"},{"name":"中山市石岐张溪郑二小学","address":"广东省中山市石岐区张溪横坑街11号","phone":"760-88613339","code":" 2144016898","nature":"小学"},{"name":"中山市石岐第一城小学","address":"广东省中山市石岐区第一城星宝街4号","phone":"760-88861020","code":" 2144016899","nature":"小学"},{"name":"中山市石岐实验小学","address":"广东省中山市石岐区七仙街2号","phone":"760-88823621","code":" 2144016901","nature":"小学"},{"name":"中山市石岐太平小学","address":"广东省中山市石岐区太平路置宏街8号","phone":"760-88832177","code":" 2144016902","nature":"小学"},{"name":"中山市石岐第一小学","address":"广东省中山市石岐区康华路5号","phone":"760-88720602","code":" 2144016904","nature":"小学"},{"name":"中山市博爱小学","address":"广东省中山市石岐区民权路55号","phone":"760-88820066","code":" 2144016905","nature":"小学"},{"name":"中山市石岐体育路学校","address":"广东省中山市东区恒宝街2号","phone":"760-88331896","code":" 2144016906","nature":"小学"},{"name":"中山市石岐杨仙逸小学","address":"广东省中山市石岐区南下坭墩下街38号","phone":"760-88802744","code":" 2144016907","nature":"小学"},{"name":"中山市东区雍景园小学","address":"广东省中山市东区岐关西路45号","phone":"760-88383180","code":" 2144016908","nature":"小学"},{"name":"中山市东区起湾学校","address":"广东省中山市东区富湾南路红棉街19号起湾小学","phone":"760-88221579","code":" 2144016910","nature":"小学"},{"name":"中山市东区柏苑中心小学","address":"广东省中山市东区柏华街12号","phone":"760-88319499","code":" 2144016911","nature":"小学"},{"name":"中山市东区竹苑小学","address":"广东省中山市东区文竹路10号","phone":"760-88322735","code":" 2144016912","nature":"小学"},{"name":"中山市东区水云轩小学","address":"广东省中山市富湾南路9号","phone":"760-88228300","code":" 2144016914","nature":"小学"},{"name":"中山市东区白沙湾学校","address":"广东省中山市东区白沙湾村白沙湾大街52号","phone":"760-88228982","code":" 2144016915","nature":"小学"},{"name":"中山市东区朗晴小学","address":"广东省中山市东区城桂路北侧（市一中初中部对面）","phone":"760-88391189","code":" 2144016916","nature":"小学"},{"name":"中山火炬高技术产业开发区第一小学","address":"广东省中山市火炬开发区张家边三村庵前街1号","phone":"760-85317788","code":" 2144016917","nature":"小学"},{"name":"中山火炬高技术产业开发区第四小学","address":"广东省中山市火炬开发区陵岗村光丰街6号","phone":"760-88283780","code":" 2144016918","nature":"小学"},{"name":"中山火炬高技术产业开发区第二小学","address":"广东省中山市火炬开发区继光路3号","phone":"760-85289802","code":" 2144016919","nature":"小学"},{"name":"中山火炬高技术产业开发区第三小学","address":"广东省中山市火炬开发区濠头一村濠头大街33号","phone":"760-85593022","code":" 2144016920","nature":"小学"},{"name":"中山火炬高技术产业开发区第五小学","address":"中山市火炬开发区环茂路48号南","phone":"760-85596882","code":" 2144016921","nature":"小学"},{"name":"中山火炬高技术产业开发区第六小学","address":"广东省中山市火炬开发区街道办事处联富社区居民委员会沙边小区上街横巷一号","phone":"760-85595350","code":" 2144016922","nature":"小学"},{"name":"中山市沙溪镇港园小学","address":"广东省中山市沙溪镇港园村校园里1号","phone":"760-87793827","code":" 2144017054","nature":"小学"},{"name":"中山市沙溪镇濠涌小学","address":"广东省中山市沙溪镇濠涌村中和上街东23号","phone":"760-87793852","code":" 2144017055","nature":"小学"},{"name":"中山市沙溪镇乐群小学","address":"广东省中山市沙溪镇乐群永厚环新村1号","phone":"760-87189908","code":" 2144017056","nature":"小学"},{"name":"中山市沙溪镇圣狮小学","address":"广东省中山市沙溪镇圣狮村村尾","phone":"760-87713396","code":" 2144017057","nature":"小学"},{"name":"中山市沙溪镇下泽小学","address":"广东省中山市沙溪镇下泽村健康街1号","phone":"760-87793875","code":" 2144017058","nature":"小学"},{"name":"中山市沙溪镇象角小学","address":"广东省中山市沙溪镇象角村民委员会象角大街3号","phone":"760-87717789","code":" 2144017059","nature":"小学"},{"name":"中山市沙溪镇云汉小学","address":"广东省中山市沙溪镇云汉村云汉大街125号","phone":"760-87793849","code":" 2144017060","nature":"小学"},{"name":"中山市沙溪镇中心小学","address":"广东省中山市沙溪镇豪吐村上堡头龙井街9号","phone":"760-87398471","code":" 2144017061","nature":"小学"},{"name":"中山市沙溪镇虎逊小学","address":"广东省中山市沙溪镇虎逊村高亮原路沙平村口","phone":"760-87392631","code":" 2144017062","nature":"小学"},{"name":"中山市申明亭学校","address":"广东省中山市沙溪镇中兴村申明亭大街29号","phone":"760-87390666","code":" 2144017063","nature":"小学"},{"name":"中山市沙溪镇康乐小学","address":"广东省中山市沙溪镇建设路168号","phone":"760-87795020","code":" 2144017064","nature":"小学"},{"name":"中山市坦洲镇林东小学","address":"中山市坦洲镇德溪路137号","phone":"760-86651404","code":" 2144017066","nature":"小学"},{"name":"中山市坦洲镇合胜小学","address":"广东省中山市坦洲镇合胜社区居民委员会(工业大道111号)侧","phone":"760-86652170","code":" 2144017067","nature":"小学"},{"name":"中山市坦洲镇安阜小学","address":"广东省中山市坦洲镇安阜街78号","phone":"760-86651066","code":" 2144017068","nature":"小学"},{"name":"中山市坦洲镇同胜小学","address":"广东省中山市坦洲镇同胜社区同旺街163号","phone":"760-86652635","code":" 2144017069","nature":"小学"},{"name":"中山市坦洲镇十四村小学","address":"广东省中山市坦洲镇十四村连仕街45号","phone":"760-86652126","code":" 2144017070","nature":"小学"},{"name":"中山市坦洲镇七村小学","address":"中山市坦洲镇七村大道42号","phone":"760-86652145","code":" 2144017071","nature":"小学"},{"name":"中山市坦洲镇永一小学","address":"中山市坦洲镇永前路27号","phone":"760-86652590","code":" 2144017072","nature":"小学"},{"name":"中山市坦洲镇永二小学","address":"广东省中山市坦洲镇永二村民委员会（祯祥街28号）","phone":"760-86651173","code":" 2144017073","nature":"小学"},{"name":"中山市坦洲镇前进小学","address":"广东省中山市坦洲镇新前进村民委员会申堂街123号","phone":"760-86651160","code":" 2144017074","nature":"小学"},{"name":"中山市坦洲镇联一小学","address":"广东省中山市坦洲镇德溪路185号","phone":"760-86651158","code":" 2144017075","nature":"小学"},{"name":"中山市坦洲镇群联小学","address":"广东省中山市坦洲镇坦群二路180号","phone":"760-86652766","code":" 2144017077","nature":"小学"},{"name":"中山市坦洲镇裕洲小学","address":"广东省中山市坦洲镇裕洲村民委员会山边街48号","phone":"760-86651458","code":" 2144017078","nature":"小学"},{"name":"中山市坦洲镇新合小学","address":"中山市坦洲镇新合村新庆街26号","phone":"760-86651958","code":" 2144017079","nature":"小学"},{"name":"中山市坦洲爱华学校","address":"广东省中山市坦洲镇坦联路78号","phone":"760-86630971","code":" 2144017081","nature":"小学"},{"name":"中山市港口镇中心小学","address":"广东省中山市港口镇民新路南88号","phone":"760-88419323","code":" 2144017083","nature":"小学"},{"name":"中山市港口镇民主小学","address":"广东省中山市港口镇民主社区乐民新村南六巷8号","phone":"760-88418846","code":" 2144017084","nature":"小学"},{"name":"中山市港口镇群众小学","address":"广东省中山市港口镇东长堤大道98号","phone":"760-88412113","code":" 2144017085","nature":"小学"},{"name":"中山市港口镇石特小学","address":"广东省中山市港口镇中村北路60号","phone":"760-88410811","code":" 2144017086","nature":"小学"},{"name":"中山市港口镇西街小学","address":"广东省中山市港口镇西街路50号","phone":"760-88402320","code":" 2144017087","nature":"小学"},{"name":"中山市港口镇大丰小学","address":"广东省中山市港口镇余庆围街73号（群乐社区居民委员会）","phone":"760-88401987","code":" 2144017089","nature":"小学"},{"name":"中山市港口镇中南小学","address":"广东省中山市港口镇中南村莲池尾181号","phone":"760-88410247","code":" 2144017090","nature":"小学"},{"name":"中山市港口镇下南小学","address":"二榕树街182号","phone":"760-88411263","code":" 2144017257","nature":"小学"},{"name":"中山市港口港源学校","address":"广东省中山市港口镇西街社区居民委员会南九大街特一号","phone":"760-88481188","code":" 2144017258","nature":"小学"},{"name":"中山市三角镇中心小学","address":"广东省中山市三角镇结民村民委员会福星路13号","phone":"760-85543132","code":" 2144017259","nature":"小学"},{"name":"中山市三角镇光明小学","address":"广东省中山市三角镇光明村裕康路18号","phone":"760-85543254","code":" 2144017260","nature":"小学"},{"name":"中山市三角镇高平小学","address":"广东省中山市三角镇高平村锦成路61号","phone":"760-85543700","code":" 2144017261","nature":"小学"},{"name":"中山市三角镇蟠龙小学","address":"广东省中山市三角镇蟠龙路2号之一","phone":"760-85543374","code":" 2144017262","nature":"小学"},{"name":"中山市三角镇沙栏小学","address":"广东省中山市三角镇沙栏西路西一巷15号","phone":"760-18928156928","code":" 2144017263","nature":"小学"},{"name":"中山市三角镇三角小学","address":"广东省中山市三角镇南坑街3号","phone":"760-85540808","code":" 2144017264","nature":"小学"},{"name":"中山市三角四海学校","address":"广东省中山市三角镇东南村东会街59号","phone":"760-80408011","code":" 2144017265","nature":"小学"},{"name":"中山市横栏镇横栏小学","address":"广东省中山市横栏镇顺兴北路3号","phone":"760-87766568","code":" 2144017266","nature":"小学"},{"name":"中山市横栏镇第二小学","address":"广东省中山市横栏镇六沙村状元新村大街1号之二","phone":"760-87766517","code":" 2144017268","nature":"小学"},{"name":"中山市横栏镇三沙小学","address":"广东省中山市横栏镇三沙村八队市场路20号（中英广场斜对面）","phone":"760-7766440","code":" 2144017270","nature":"小学"},{"name":"中山市横栏港源学校","address":"广东省中山市横栏镇发展路宝裕村民委员会特1号","phone":"760-87298899","code":" 2144017271","nature":"小学"},{"name":"中山市横栏镇四沙小学","address":"广东省中山市横栏镇新茂村德龙路育才街1号","phone":"760-87688222","code":" 2144017273","nature":"小学"},{"name":"中山市横栏华文学校","address":"广东省中山市横栏镇新茂村新兴北路203号","phone":"760-87680608","code":" 2144017274","nature":"小学"},{"name":"中山市南头镇民安小学","address":"广东省中山市南头镇民安社区居民委员会民安路90号","phone":"760-23125681","code":" 2144017275","nature":"小学"},{"name":"中山市南头镇中心小学","address":"广东省中山市南头镇同乐路广济医院旁边","phone":"760-23127118","code":" 2144017276","nature":"小学"},{"name":"中山市南头镇将军小学","address":"广东省中山市南头镇将军社区居民委员会合益西路1号","phone":"760-23113812","code":" 2144017277","nature":"小学"},{"name":"中山市南头镇升辉小学","address":"广东省中山市南头镇穗西社区居民委员会","phone":"760-23122171","code":" 2144017278","nature":"小学"},{"name":"中山市阜沙镇阜沙中心小学","address":"广东省中山市阜沙镇永红街152号","phone":"760-23403523","code":" 2144017279","nature":"小学"},{"name":"中山市阜沙镇丰联小学","address":"广东省中山市阜沙镇丰联银河村1号","phone":"760-23400581","code":" 2144017280","nature":"小学"},{"name":"中山市阜沙镇罗松小学","address":"广东省中山市阜沙镇罗松村民委员会16队（阜港西路32号）","phone":"760-23406172","code":" 2144017281","nature":"小学"},{"name":"中山市阜沙镇牛角小学","address":"广东省中山市阜沙镇牛角村育才路3号","phone":"760-23401305","code":" 2144017282","nature":"小学"},{"name":"中山市南朗街道翠亨小学","address":"广东省中山市南朗镇翠亨村沙园路10号","phone":"760-85501103","code":" 2144017284","nature":"小学"},{"name":"中山市南朗街道横门小学","address":"广东省中山市南朗镇横门十顷村海富中路29号","phone":"760-23392692","code":" 2144017285","nature":"小学"},{"name":"中山市南朗街道榄边小学","address":"广东省中山市南朗镇榄边村民委员会茶西村圣堂大街（榄边幼儿园旁）","phone":"760-85523349","code":" 2144017286","nature":"小学"},{"name":"中山市南朗街道云衢小学","address":"广东省中山市南朗镇美景大道46号","phone":"760-85520881","code":" 2144017287","nature":"小学"},{"name":"中山市南朗街道南朗小学","address":"广东省中山市南朗镇龙穴路亨美祥和巷1号","phone":"760-86628203","code":" 2144017288","nature":"小学"},{"name":"中山市三乡镇白石环小学","address":"广东省中山市三乡镇白石教育路10号","phone":"760-86686938","code":" 2144017290","nature":"小学"},{"name":"中山市三乡镇平岚小学","address":"广东省中山市三乡镇忠堡街36号","phone":"760-86684976","code":" 2144017291","nature":"小学"},{"name":"中山市三乡镇载德小学","address":"广东省中山市三乡镇小琅环路","phone":"760-86692725","code":" 2144017292","nature":"小学"},{"name":"中山市三乡镇鸦岗小学","address":"广东省中山市三乡镇岗泉村民委员会鸦岗村景福巷34号","phone":"760-86685464","code":" 2144017293","nature":"小学"},{"name":"中山市三乡镇新圩小学","address":"广东省中山市三乡镇新圩村盛业路3号","phone":"760-86683754","code":" 2144017294","nature":"小学"},{"name":"中山市三乡镇雍陌小学","address":"广东省中山市三乡镇雍陌村教育路1号（中国）","phone":"760-86331173","code":" 2144017295","nature":"小学"},{"name":"中山市三乡镇大布小学","address":"广东省中山市三乡镇大布村校前街1号","phone":"760-86684573","code":" 2144017296","nature":"小学"},{"name":"中山市三乡镇光后中心小学","address":"广东省中山市三乡镇金光大道1号","phone":"760-86693763","code":" 2144017297","nature":"小学"},{"name":"中山市三乡新民学校","address":"广东省中山市三乡镇古鹤村居委会鹤前南路28号","phone":"760-86685356","code":" 2144017300","nature":"小学"},{"name":"中山市三乡东华学校","address":"广东省中山市三乡镇东桂村民委员西山路161号","phone":"760-86328753","code":" 2144017301","nature":"小学"},{"name":"中山市板芙镇湖洲小学","address":"广东省中山市板芙镇湖洲村中心街8号","phone":"760-86501120","code":" 2144017302","nature":"小学"},{"name":"中山市板芙镇深湾小学","address":"广东省中山市板芙镇深湾村迎阳路2号","phone":"760-86508110","code":" 2144017303","nature":"小学"},{"name":"中山市板芙镇广福小学","address":"广东省中山市板芙镇广福村大围一街11号","phone":"760-86508070","code":" 2144017304","nature":"小学"},{"name":"中山市板芙镇板芙小学","address":"广东省中山市板芙镇板芙村光阳路2号","phone":"760-86501042","code":" 2144017305","nature":"小学"},{"name":"中山市板芙镇新联小学","address":"广东省中山市板芙镇板尾村新联小学","phone":"760-86508047","code":" 2144017307","nature":"小学"},{"name":"中山市大涌镇岚田中心小学","address":"广东省中山市大涌镇环镇路岚田路段北120号","phone":"760-87725414","code":" 2144017309","nature":"小学"},{"name":"中山市大涌南文小学","address":"广东省中山市大涌镇旗山路437号","phone":"760-87725524","code":" 2144017310","nature":"小学"},{"name":"中山市大涌镇安堂小学","address":"广东省中山市大涌镇安堂社区居民委员会","phone":"760-87725320","code":" 2144017311","nature":"小学"},{"name":"中山市大涌镇旗南小学","address":"广东省中山市大涌镇旗南村见龙南街6号","phone":"760-87725924","code":" 2144017312","nature":"小学"},{"name":"中山市大涌镇旗北小学","address":"广东省中山市大涌镇青岗村韶化西街20号","phone":"760-87771699","code":" 2144017314","nature":"小学"},{"name":"中山市神湾镇神湾中心小学","address":"广东省中山市神湾镇南沙工业区园丁路1号","phone":"760-86605363","code":" 2144017315","nature":"小学"},{"name":"中山市石岐中心小学","address":"广东省中山市东区东文路2号","phone":"760-88387516","code":" 2144017318","nature":"小学"},{"name":"中山市实验小学","address":"广东省中山市石岐区东盛花园32号","phone":"760-88722022","code":" 2144017319","nature":"小学"},{"name":"中山火炬高技术产业开发区新苗学校","address":"广东省中山市火炬开发区中山港大道窈窕村路段金华花园旁边50米","phone":"760-88298099","code":" 2144020577","nature":"小学"},{"name":"中山火炬高技术产业开发区中心小学","address":"广东省中山市火炬开发区康乐四街11号","phone":"760-28139162","code":" 2144020579","nature":"小学"},{"name":"中山市西区西区小学","address":"中山市西区升华道10号","phone":"760-28131012","code":" 2144020580","nature":"小学"},{"name":"中山市西区烟洲小学","address":"广东省中山市西区街道办事处长洲社区居民委员会石台街4号","phone":"760-88638486","code":" 2144020581","nature":"小学"},{"name":"中山市西区昌平小学","address":"中山市西区沙朗粤信路6号","phone":"760-88558510","code":" 2144020582","nature":"小学"},{"name":"中山市西区沙朗小学","address":"广东省中山市西区沙朗悦和路5号","phone":"760-88558932","code":" 2144020583","nature":"小学"},{"name":"中山市西区翠景东方小学","address":"广东省中山市西区翠景道翠湖路1号","phone":"760-88610921","code":" 2144020584","nature":"小学"},{"name":"中山市蓝波湾学校","address":"广东省中山市西区江湾路8号","phone":"760-88628827","code":" 2144020588","nature":"小学"},{"name":"中山市西区中心小学","address":"广东省中山市西区街道办事处翠虹路6号","phone":"760-88621007","code":" 2144020589","nature":"小学"},{"name":"中山市南区竹秀园中心小学","address":"广东省中山市南区竹秀园栋梁街1号","phone":"760-88899938","code":" 2144020590","nature":"小学"},{"name":"中山市南区良都小学","address":"广东省中山市南区兴福路2号","phone":"760-23331186","code":" 2144020591","nature":"小学"},{"name":"中山市南区北台小学","address":"广东省中山市南区街道办事处北台社区居民委员会凤鸣街向前30米","phone":"760-23334462","code":" 2144020592","nature":"小学"},{"name":"中山市恒美学校","address":"广东省中山市南区拱北大街61号","phone":"760-88891463","code":" 2144020593","nature":"小学"},{"name":"中山市小榄镇中心小学","address":"广东省中山市小榄镇新市社区居民委员会诗礼街6号","phone":"760-23313166","code":" 2144020598","nature":"小学"},{"name":"中山市小榄镇永康小学","address":"广东省中山市小榄镇永进路60号","phone":"760-22278070","code":" 2144020599","nature":"小学"},{"name":"中山市小榄镇永宁中心小学","address":"广东省中山市小榄镇永宁北村大街113号","phone":"760-22252757","code":" 2144020600","nature":"小学"},{"name":"中山市小榄镇北区小学","address":"广东省中山市小榄镇北区盛丰街16号","phone":"760-22275891","code":" 2144020601","nature":"小学"},{"name":"中山市小榄镇绩东一小学","address":"中山市小榄镇成发路6号","phone":"760-22242505","code":" 2144020603","nature":"小学"},{"name":"中山市小榄镇绩西小学","address":"广东省中山市小榄镇绩西祥安路1号","phone":"760-22245349","code":" 2144020604","nature":"小学"},{"name":"中山市小榄镇九洲基小学","address":"广东省中山市小榄镇育才路483号","phone":"760-22287870","code":" 2144020605","nature":"小学"},{"name":"中山市小榄镇联丰小学","address":"广东省中山市小榄镇联丰乐安东路11号","phone":"760-22551361","code":" 2144020607","nature":"小学"},{"name":"中山市小榄镇埒西一小学","address":"广东省中山市小榄镇广丰北路94号","phone":"760-22245622","code":" 2144020608","nature":"小学"},{"name":"中山市小榄镇德星小学","address":"广东省中山市小榄镇东堤路德星里20号","phone":"760-22253642","code":" 2144020609","nature":"小学"},{"name":"中山市小榄镇西区小学","address":"广东省中山市小榄镇新教路1号","phone":"760-22233599","code":" 2144020610","nature":"小学"},{"name":"中山市小榄镇竹源小学","address":"广东省中山市小榄镇科教路2号","phone":"760-22254149","code":" 2144020611","nature":"小学"},{"name":"中山市菊城小学","address":"广东省中山市小榄镇民安南路148号","phone":"760-22286383","code":" 2144020612","nature":"小学"},{"name":"中山市小榄镇绩东二小学","address":"广东省中山市小榄镇绩东二星怡路149号","phone":"760-22245410","code":" 2144020613","nature":"小学"},{"name":"中山市小榄镇升平小学","address":"广东省中山市小榄镇荣华中路19号","phone":"760-22130613","code":" 2144020614","nature":"小学"},{"name":"中山市小榄镇盛丰小学","address":"广东省中山市小榄镇盛丰成学路10号","phone":"760-22286930","code":" 2144020615","nature":"小学"},{"name":"中山市小榄吉安学校","address":"广东省中山市小榄镇联丰社区聚民街38号","phone":"760-22280403","code":" 2144020619","nature":"小学"},{"name":"中山市小榄广源学校","address":"广东省中山市小榄镇广源南路38号","phone":"760-22182283","code":" 2144020620","nature":"小学"},{"name":"中山市小榄丰华学校","address":"广东省中山市小榄镇工业大道中宝城路26号","phone":"760-22122695","code":" 2144020621","nature":"小学"},{"name":"中山市黄圃镇新地中心小学","address":"广东省中山市黄圃镇新地村新地大道89号","phone":"760-23226091","code":" 2144020624","nature":"小学"},{"name":"中山市黄圃镇马安小学","address":"广东省中山市黄圃镇马安村正学街2号","phone":"760-23229242","code":" 2144020625","nature":"小学"},{"name":"中山市黄圃镇培红小学","address":"广东省中山市黄圃镇环山中路1号","phone":"760-23239023","code":" 2144020626","nature":"小学"},{"name":"中山市黄圃镇团范小学","address":"广东省中山市黄圃镇团范村民委员会同安街一号","phone":"760-23229340","code":" 2144020627","nature":"小学"},{"name":"中山市黄圃镇大岑小学","address":"广东省中山市黄圃镇大岑村大兴中路49号之一","phone":"760-23219241","code":" 2144020628","nature":"小学"},{"name":"中山市黄圃镇对甫小学","address":"广东省中山市黄圃镇对甫街222号","phone":"760-23226605","code":" 2144020629","nature":"小学"},{"name":"中山市黄圃镇横档小学","address":"广东省中山市黄圃镇横档村人富街2号","phone":"760-23221255","code":" 2144020630","nature":"小学"},{"name":"中山市黄圃镇石军小学","address":"广东省中山市黄圃镇石军村怡隆街57号之一","phone":"760-23221246","code":" 2144020631","nature":"小学"},{"name":"中山市黄圃镇吴栏小学","address":"广东省中山市黄圃镇吴栏村良涌北街86号","phone":"760-23219240","code":" 2144020632","nature":"小学"},{"name":"中山市黄圃镇新沙小学","address":"广东省中山市黄圃镇新沙村安庆中街1号","phone":"760-23226829","code":" 2144020633","nature":"小学"},{"name":"中山市黄圃镇大雁小学","address":"广东省中山市黄圃镇兴雁北街60号","phone":"760-23219347","code":" 2144020634","nature":"小学"},{"name":"中山市黄圃雏鹰学校","address":"广东省中山市黄圃镇新糖社区居民委员会新明南路148号","phone":"760-23239839","code":" 2144020635","nature":"小学"},{"name":"中山市民众街道民众中心小学","address":"广东省中山市民众镇文化路39号","phone":"760-85708892","code":" 2144020637","nature":"小学"},{"name":"中山市民众街道育才小学","address":"广东省中山市民众镇文化路18号","phone":"760-85703160","code":" 2144020638","nature":"小学"},{"name":"中山市民众街道新平小学","address":"广东省中山市民众镇新平路38号","phone":"760-85573273","code":" 2144020639","nature":"小学"},{"name":"中山市民众街道浪网小学","address":"广东省中山市民众镇三源路3号","phone":"760-85603911","code":" 2144020641","nature":"小学"},{"name":"中山市民众街道接源小学","address":"广东省中山市民众镇接源村民委员会接福路222号","phone":"760-85555901","code":" 2144020643","nature":"小学"},{"name":"中山市民众正德学校","address":"广东省中山市民众镇浪网大道460号","phone":"760-85602698","code":" 2144020645","nature":"小学"},{"name":"中山市东凤镇中心小学","address":"广东省中山市东凤镇永安路131号","phone":"760-22600735","code":" 2144020647","nature":"小学"},{"name":"中山市东凤镇同安小学","address":"广东省中山市东凤镇兴安路37号","phone":"760-22636369","code":" 2144020648","nature":"小学"},{"name":"中山市东凤镇安乐小学","address":"广东省中山市东凤镇安乐中一路39号","phone":"760-22601064","code":" 2144020649","nature":"小学"},{"name":"中山市东凤镇民和小学","address":"广东省中山市东凤镇民乐大道35号","phone":"760-22781601","code":" 2144020650","nature":"小学"},{"name":"中山市东凤镇小沥小学","address":"广东省中山市东凤镇东海路73号","phone":"760-22601221","code":" 2144020651","nature":"小学"},{"name":"中山市东凤镇凤鸣小学","address":"广东省中山市东凤镇东阜四路26号（中国）","phone":"760-22626068","code":" 2144020653","nature":"小学"},{"name":"中山市东凤镇永益小学","address":"广东省中山市东凤镇永益村永中路42号","phone":"760-22600100","code":" 2144020654","nature":"小学"},{"name":"中山市东凤镇吉昌小学","address":"广东省中山市东凤镇吉昌村吉昌路8号","phone":"760-22600961","code":" 2144020655","nature":"小学"},{"name":"中山市东凤镇东罟小学","address":"广东省中山市东凤镇东罟一街145号","phone":"760-22601461","code":" 2144020656","nature":"小学"},{"name":"中山市东凤镇西罟小学","address":"中山市东凤镇西罟大道59号之十","phone":"760-22600314","code":" 2144020657","nature":"小学"},{"name":"中山市小榄镇高沙小学","address":"广东省中山市东升镇高沙村联胜南路17号","phone":"760-22223329","code":" 2144020659","nature":"小学"},{"name":"中山市小榄镇利生小学","address":"广东省中山市东升镇利园路31号","phone":"760-88508661","code":" 2144020660","nature":"小学"},{"name":"中山市小榄镇胜龙小学","address":"广东省中山市东升镇龙成路22号（胜龙派出所对面）","phone":"760-88500931","code":" 2144020661","nature":"小学"},{"name":"中山市小榄镇坦背小学","address":"广东省中山市小榄镇坦背村兴隆一路111号","phone":"760-88508749","code":" 2144020662","nature":"小学"},{"name":"中山市小榄镇同乐小学","address":"中山市小榄镇同乐路50号","phone":"760-22221631","code":" 2144020663","nature":"小学"},{"name":"中山市小榄镇同茂小学","address":"广东省中山市东升镇同茂五队三益街78号","phone":"760-88508773","code":" 2144020664","nature":"小学"},{"name":"中山市小榄镇东升小学","address":"广东省中山市小榄镇东升社区东升北路57号","phone":"760-22225745","code":" 2144020665","nature":"小学"},{"name":"中山市小榄镇裕民小学","address":"广东省中山市东升镇裕民社区居民委员会裕安路3号","phone":"760-22228545","code":" 2144020666","nature":"小学"},{"name":"中山市小榄镇兆隆小学","address":"广东省中山市小榄镇兆龙社区兆隆中路1号之一","phone":"760-22227124","code":" 2144020667","nature":"小学"},{"name":"中山市小榄镇东方小学","address":"广东省中山市东升镇裕民社区居民委员会东港大道6号","phone":"760-22215185","code":" 2144020668","nature":"小学"},{"name":"中山市小榄镇太平小学","address":"广东省中山市小榄镇太平路泰兴街5号","phone":"760-88507315","code":" 2144020669","nature":"小学"},{"name":"中山市小榄镇益隆小学","address":"广东省中山市小榄镇益隆村益民路兴群街78号","phone":"760-22226242","code":" 2144020670","nature":"小学"},{"name":"中山市小榄镇新胜小学","address":"广东省中山市东升镇东成路102号","phone":"760-22226077","code":" 2144020671","nature":"小学"},{"name":"中山市东升华盛学校","address":"广东省中山市东升镇永俊街10号","phone":"760-8506991","code":" 2144020672","nature":"小学"},{"name":"中山市东升桦珑学校","address":"广东省中山市小榄镇东升高沙联胜南路5号","phone":"760-22217901","code":" 2144020674","nature":"小学"},{"name":"中山市古镇镇古一小学","address":"广东省中山市古镇镇古一村中心大道1号","phone":"760-22357601","code":" 2144020675","nature":"小学"},{"name":"中山市古镇镇镇南小学","address":"中山市古镇镇中心路西十一巷10号","phone":"760-22357606","code":" 2144020678","nature":"小学"},{"name":"中山市古镇镇曹一小学","address":"广东省中山市古镇镇曹一大道24号","phone":"760-22349060","code":" 2144020679","nature":"小学"},{"name":"中山市古镇镇曹二小学","address":"广东省中山市古镇镇曹二村文化路13号","phone":"760-22395512","code":" 2144020680","nature":"小学"},{"name":"中山市古镇镇曹三小学","address":"广东省中山市古镇镇曹三工业区同益路1号","phone":"760-22397613","code":" 2144020681","nature":"小学"},{"name":"中山市古镇镇海洲第一小学","address":"广东省中山市古镇镇海洲大昆山侧","phone":"760-22315982","code":" 2144020682","nature":"小学"},{"name":"中山市古镇镇海洲第二小学","address":"广东省中山市古镇镇海洲居委会胜利二路47号","phone":"760-22317787","code":" 2144020683","nature":"小学"},{"name":"中山市古镇镇古二小学","address":"广东省中山市古镇镇永昌东一街1号","phone":"760-22357602","code":" 2144020685","nature":"小学"},{"name":"中山市古镇镇古三小学","address":"广东省中山市古镇镇古三村北苑路1号","phone":"760-22357603","code":" 2144020687","nature":"小学"},{"name":"中山市沙溪镇龙瑞小学","address":"广东省中山市沙溪镇龙瑞村学园街1号","phone":"760-87793577","code":" 2144020688","nature":"小学"},{"name":"中山市沙溪镇龙头环学校","address":"广东省中山市沙溪镇龙头环村下街2号","phone":"760-87795011","code":" 2144020689","nature":"小学"},{"name":"中山市民众街道三民学校","address":"广东省中山市民众镇义仓村义仓路1号","phone":"760-28114501","code":" 2144040407","nature":"小学"},{"name":"中山火炬高技术产业开发区香晖园小学","address":"中山市火炬开发区石牛路2号","phone":"760-88292291","code":" 2144040408","nature":"小学"},{"name":"中山市东区紫岭小学","address":"中山市东区后塘路28号","phone":"760-88861135","code":" 3144003508","nature":"小学"},{"name":"中山市小榄博华特殊教育学校","address":"广东省中山市小榄镇盛丰社区居民委员会","phone":"760-22101131","code":" 5144000090","nature":"其他学校"},{"name":"中山市特殊教育学校","address":"广东省中山市东区沙石公路6号","phone":"760-88819006","code":" 5144000091","nature":"其他学校"},{"name":"中山市光正实验学校","address":"中山市光正实验学校","phone":"760-88968868","code":" 3144004084","nature":"十二年一贯制学校"},{"name":"中山市三鑫学校","address":"广东省中山市三乡镇平南村谷都大道1136号","phone":"760-86333888","code":" 3444000143","nature":"十二年一贯制学校"},{"name":"中山市杨仙逸中学","address":"广东省中山市石岐区南下三级石11号","phone":"760-88804053","code":" 3444000679","nature":"高级中学"},{"name":"中山市东区中学","address":"中山市东区孙文东路齐乐路3号","phone":"760-88339441","code":" 3444000680","nature":"高级中学"},{"name":"中山市濠头中学（中山市艺术学校）","address":"广东省中山市火炬开发区濠东路18号","phone":"760-85596260","code":" 3444000681","nature":"高级中学"},{"name":"中山市小榄中学","address":"广东省中山市小榄镇永宁永盛路2号","phone":"760-22124954","code":" 3444000684","nature":"高级中学"},{"name":"中山市第二中学","address":"广东省中山市黄圃镇龙安街82号","phone":"760-23216215","code":" 3444000686","nature":"高级中学"},{"name":"中山市民众德恒学校","address":"广东省中山市民众镇多宝社区居民委员会浪源路2号","phone":"760-85602999","code":" 3444000688","nature":"十二年一贯制学校"},{"name":"中山市东升高级中学","address":"中山市东升镇同乐路28号","phone":"760-22820000","code":" 3444000689","nature":"高级中学"},{"name":"中山市古镇高级中学","address":"中山市古镇镇海洲村西岸北路52号","phone":"760-22362101","code":" 3444000690","nature":"高级中学"},{"name":"中山市龙山中学","address":"广东省中山市沙溪镇宝珠东路75号","phone":"760-28118967","code":" 3444000691","nature":"高级中学"},{"name":"中山市桂山中学","address":"广东省中山市三乡镇小琅环路38号","phone":"760-86685105","code":" 3444000694","nature":"高级中学"},{"name":"中山市中山纪念中学","address":"广东省中山市南朗镇翠亨村纪中校道1号","phone":"760-85501869","code":" 3444000695","nature":"完全中学"},{"name":"中山市第一中学","address":"广东省中山市东区兴文路68号（东裕社区居民委员会）","phone":"760-88332635","code":" 3444000696","nature":"完全中学"},{"name":"中山市华侨中学","address":"广东省中山市石岐区民族东路18号","phone":"760-88700302","code":" 3444000697","nature":"完全中学"},{"name":"中山市实验中学","address":"广东省中山市东区街道办事处东江路12号","phone":"760-88331091","code":" 3444000698","nature":"完全中学"},{"name":"中山市广东博文学校","address":"广东省中山市火炬开发区博爱七路96号","phone":"760-85316013","code":" 3444000700","nature":"十二年一贯制学校"},{"name":"中山市中港英文学校","address":"广东省中山市五桂山街道长命水大街2号","phone":"760-23378780","code":" 3444000701","nature":"十二年一贯制学校"},{"name":"中山市华辰实验中学","address":"口镇美景东路1号(中学校区) 、中山市港口镇民主一街1号（小学校区）","phone":"760-88418339","code":" 3444000702","nature":"十二年一贯制学校"},{"name":"中山市迪茵公学","address":"广东省中山市三角镇金三大道东21号","phone":"760-86183886","code":" 3444000811","nature":"十二年一贯制学校"},{"name":"中山市西湾外国语学校","address":"","phone":"760-28218551","code":" 3444001032","nature":"十二年一贯制学校"},{"name":"中山市卓雅外国语学校","address":"","phone":"760-88291007","code":" 3444001144","nature":"高级中学"},{"name":"中山市永安中学","address":"","phone":"760-88818000","code":" 3444001190","nature":"高级中学"},{"name":"中山市烟洲中学","address":"","phone":"760-28211985","code":" 3444001218","nature":"高级中学"},{"name":"中山市弘科未来学校","address":"","phone":"760-13356420707","code":" 3444001249","nature":"十二年一贯制学校"},{"name":"电子科技大学中山学院","address":"广东省中山市石岐区学院路1号\t","phone":"0760\t-88311016\t","code":"4144011545","nature":"本科院校"},{"name":"中山火炬职业技术学院","address":"广东省中山市火炬开发区街道办事处张家边社区居民委员会\t","phone":"0760\t-88291180\t","code":"4144013710","nature":"专科院校"},{"name":"中山职业技术学院","address":"广东省中山市东区博爱七路25号\t","phone":"0760\t-87500913\t","code":"4144014066","nature":"专科院校"},{"name":"中山市南头三鑫学校","address":"广东省中山市南头镇德业路32号","phone":"760-89836666","code":" 2144001895","nature":"九年一贯制学校"},{"name":"中山市东区远洋学校","address":"中山市东区扬逸路50号","phone":"760-88265822","code":" 2144003022","nature":"九年一贯制学校"},{"name":"中山市坦洲中茂学校","address":"广东省中山市坦洲镇中澳新城界狮南路6号","phone":"760-85762233","code":" 2144010551","nature":"九年一贯制学校"},{"name":"中山市大信学校","address":"广东省中山市石岐区兴盛路3号","phone":"760-88792333","code":" 2144017325","nature":"九年一贯制学校"},{"name":"中山市三鑫凯茵学校","address":"广东省中山市火炬开发区宫花村凯茵新城淘金街外环路旁","phone":"760-88889188","code":" 2144020578","nature":"九年一贯制学校"},{"name":"中山市古镇新徽学校","address":"广东省中山市古镇镇海洲村北海路25号","phone":"760-22315195","code":" 2144020686","nature":"九年一贯制学校"},{"name":"中山市丽景学校","address":"广东省中山市小榄镇丽景路9号","phone":"760-22736666","code":" 3144000270","nature":"九年一贯制学校"},{"name":"中山市石岐启发初级中学","address":"广东省中山市石岐区孙文中路龙母庙街70号","phone":"760-88822198","code":" 3144001944","nature":"初级中学"},{"name":"中山市石岐中学","address":"广东省中山市石岐区康华路1号","phone":"760-88704883","code":" 3144001945","nature":"初级中学"},{"name":"中山市北区中学","address":"广东省中山市石岐区湖滨中路5号","phone":"760-23328862","code":" 3144001946","nature":"初级中学"},{"name":"中山市东区松苑中学","address":"广东省中山市东区松苑路彩虹街1号","phone":"760-88389909","code":" 3144001947","nature":"初级中学"},{"name":"中山市东区团益学校","address":"广东省中山市东区亨尾横街168号","phone":"760-88231698","code":" 3144001948","nature":"九年一贯制学校"},{"name":"中山火炬高技术产业开发区第一中学","address":"中山市火炬开发区世纪一路","phone":"760-89933652","code":" 3144001949","nature":"初级中学"},{"name":"中山市育英学校","address":"广东省中山市火炬开发区街道办事处海滨社区居民委员会珊洲村新村三巷与校前街交叉口西50米","phone":"760-88283118","code":" 3144001950","nature":"九年一贯制学校"},{"name":"中山市西区初级中学","address":"广东省中山市西区翠宝路5号","phone":"760-88625973","code":" 3144001951","nature":"初级中学"},{"name":"中山市西区聚星学校","address":"广东省中山市西区街道办事处隆平社区居民委员会","phone":"760-88558557","code":" 3144001952","nature":"九年一贯制学校"},{"name":"中山市广浩学校","address":"中山市西区街道办事处沙朗社区金港路","phone":"760-88160671","code":" 3144001953","nature":"九年一贯制学校"},{"name":"中山市新长江学校","address":"广东省中山市西区沙朗悦和路188号","phone":"762-88660173","code":" 3144001954","nature":"九年一贯制学校"},{"name":"中山市良都中学","address":"广东省中山市南区上塘竹基街1号","phone":"760-23335087","code":" 3144001955","nature":"初级中学"},{"name":"中山市南侨英才学校","address":"广东省中山市南区情景路1号","phone":"760-88960896","code":" 3144001956","nature":"九年一贯制学校"},{"name":"中山市龙泉学校","address":"广东省中山市五桂山镇长命水村龙井路1号","phone":"760-88205820","code":" 3144001957","nature":"九年一贯制学校"},{"name":"中山市五桂山桂南学校","address":"广东省中山市五桂山镇桂南马溪村环村西路3号","phone":"760-18925363661","code":" 3144001958","nature":"九年一贯制学校"},{"name":"中山市小榄镇第二中学","address":"广东省中山市小榄镇联丰南路2号","phone":"760-22286915","code":" 3144001959","nature":"初级中学"},{"name":"中山市小榄镇华侨中学","address":"广东省中山市小榄镇竹源社区宝源路石岗2号","phone":"760-22280951","code":" 3144001960","nature":"初级中学"},{"name":"中山市永宁中学","address":"广东省中山市小榄镇永宁永福路2号","phone":"760-22253806","code":" 3144001961","nature":"初级中学"},{"name":"中山市小榄镇第一中学","address":"广东省中山市小榄镇新华西路5号","phone":"760-22118010","code":" 3144001962","nature":"初级中学"},{"name":"中山市小榄镇菊城中学","address":"广东省中山市小榄镇横滨路28号","phone":"760-22136001","code":" 3144001963","nature":"初级中学"},{"name":"中山市翔鸿学校","address":"广东省中山市小榄镇祥丰中路2号","phone":"760-22247882","code":" 3144001964","nature":"九年一贯制学校"},{"name":"中山市小榄花城中学","address":"广东省中山市小榄镇永宁永盛路2号","phone":"760-86182525","code":" 3144001965","nature":"初级中学"},{"name":"中山市小榄东阳学校","address":"中山市小榄镇九洲基广成路321号","phone":"760-22279288","code":" 3144001966","nature":"九年一贯制学校"},{"name":"中山市小榄福兴学校","address":"广东省中山市小榄镇北区社区居民委员会接龙路8号","phone":"760-22831206","code":" 3144001967","nature":"九年一贯制学校"},{"name":"中山市小榄华晖学校","address":"广东省中山市小榄镇永宁社区教育路3号","phone":"760-22558606","code":" 3144001968","nature":"九年一贯制学校"},{"name":"中山市黄圃镇马新初级中学","address":"广东省中山市黄圃镇马安村二河裕河北街35号","phone":"760-23229594","code":" 3144001969","nature":"初级中学"},{"name":"中山市黄圃镇中学","address":"广东省中山市黄圃镇新地村新柳西路1号","phone":"760-22501341","code":" 3144001970","nature":"初级中学"},{"name":"中山市黄圃华洋学校","address":"广东省中山市黄圃镇鳌山村南阳西街5号","phone":"760-23222101","code":" 3144001971","nature":"九年一贯制学校"},{"name":"中山市浪网中学","address":"广东省中山市民众街道浪网村阳光大道133号","phone":"760-85558203","code":" 3144001972","nature":"初级中学"},{"name":"中山市民众锦标学校","address":"广东省中山市民众镇锦标村锦丰东路82号","phone":"760-85575556","code":" 3144001974","nature":"九年一贯制学校"},{"name":"中山市东凤中学","address":"广东省中山市东凤镇东阜二路198号","phone":"760-22600497","code":" 3144001975","nature":"初级中学"},{"name":"中山市东凤镇第二中学","address":"中山市东凤镇东和路26号","phone":"760-22638991","code":" 3144001976","nature":"初级中学"},{"name":"中山市东凤穗成新徽学校","address":"广东省中山市东凤镇穗成村穗成路42号","phone":"760-22637248","code":" 3144001977","nature":"九年一贯制学校"},{"name":"中山市东凤东海学校","address":"广东省中山市东凤镇小沥村东海五路普富街22号","phone":"760-22608935","code":" 3144001978","nature":"九年一贯制学校"},{"name":"中山市小榄镇东升初级中学","address":"广东省中山市小榄镇东升同乐路28号","phone":"760-89818967","code":" 3144001979","nature":"初级中学"},{"name":"中山市坦洲华特雅学校","address":"广东省中山市坦洲镇沾涌村青砖屋街27号","phone":"760-86218888","code":" 3144002145","nature":"九年一贯制学校"},{"name":"中山市小榄镇旭日初级中学","address":"广东省中山市东升镇勤政路23号","phone":"760-22213805","code":" 3144002146","nature":"初级中学"},{"name":"中山市东升求实学校","address":"广东省中山市小榄镇东升片新胜村永新路10号","phone":"760-22220111","code":" 3144002147","nature":"九年一贯制学校"},{"name":"中山市古镇学校","address":"中山市古镇镇古四校园路28号","phone":"760-22357306","code":" 3144002148","nature":"九年一贯制学校"},{"name":"中山市曹步初级中学","address":"广东省中山市古镇镇曹一村西安上街14巷36号","phone":"760-22397113","code":" 3144002149","nature":"初级中学"},{"name":"中山市海洲初级中学","address":"广东省中山市古镇镇海兴路83号","phone":"760-22317746","code":" 3144002150","nature":"初级中学"},{"name":"中山市沙溪初级中学","address":"广东省中山市沙溪镇康乐中路8号","phone":"760-87327890","code":" 3144002151","nature":"初级中学"},{"name":"中山市溪角初级中学","address":"广东省中山市沙溪镇新濠路93号","phone":"760-87793477","code":" 3144002152","nature":"初级中学"},{"name":"中山市沙溪华强学校","address":"广东省中山市沙溪镇龙头环村花园大街35号","phone":"760-86236962","code":" 3144002153","nature":"九年一贯制学校"},{"name":"中山市坦洲中学","address":"广东省中山市坦洲镇德溪路189号","phone":"760-86655886","code":" 3144002154","nature":"初级中学"},{"name":"中山市坦洲实验中学","address":"广东省中山市坦洲镇青晖路1号","phone":"760-86637628","code":" 3144002155","nature":"初级中学"},{"name":"中山市坦洲镇第三初级中学","address":"广东省中山市坦洲镇裕洲村南村街7号","phone":"760-86652235","code":" 3144002156","nature":"初级中学"},{"name":"中山市广大汇翠学校","address":"广东省中山市坦洲镇南坦路180号汇翠山庄里","phone":"760-86210188","code":" 3144002473","nature":"九年一贯制学校"},{"name":"中山市坦洲明德学校","address":"广东省中山市坦洲镇新前进村火炬路22号","phone":"760-86688051","code":" 3144002474","nature":"九年一贯制学校"},{"name":"中山市港口中学","address":"广东省中山市港口镇南八大街1号","phone":"760-88409985","code":" 3144002475","nature":"初级中学"},{"name":"中山市港口镇大南中学","address":"广东省中山市港口镇福源路公平村路口1号","phone":"760-88400918","code":" 3144002476","nature":"初级中学"},{"name":"中山市三角中学","address":"广东省中山市三角镇岗北南路1号","phone":"760-85542200","code":" 3144002477","nature":"初级中学"},{"name":"中山市沙栏初级中学","address":"广东省中山市三角镇沙栏西路67号","phone":"760-85549882","code":" 3144002478","nature":"初级中学"},{"name":"中山市南头镇初级中学","address":"中山市南头镇升辉南路26号","phone":"760-23125383","code":" 3144002480","nature":"初级中学"},{"name":"中山市阜沙中学","address":"广东省中山市阜沙镇阜港东路旁","phone":"760-23401531","code":" 3144002481","nature":"初级中学"},{"name":"中山市牛角初级中学","address":"广东省中山市阜沙镇育才路1号","phone":"760-23401591","code":" 3144002482","nature":"初级中学"},{"name":"中山市阜沙鹏诚学校","address":"广东省中山市阜沙镇上南村鹏诚学校","phone":"760-23452360","code":" 3144002483","nature":"九年一贯制学校"},{"name":"中山市南朗街道云衢中学","address":"广东省中山市南朗镇逸翠路10号","phone":"760-85521281","code":" 3144002484","nature":"初级中学"},{"name":"中山市三乡镇初级中学","address":"广东省中山市三乡镇金涌大道23号","phone":"760-86329037","code":" 3144002485","nature":"初级中学"},{"name":"中山市博爱初级中学","address":"广东省中山市三乡镇雍陌村教育路2号","phone":"760-86684340","code":" 3144002486","nature":"初级中学"},{"name":"中山市三乡平东学校","address":"广东省中山市三乡镇平岚东村民委员会教育路2号","phone":"760-86338876","code":" 3144002487","nature":"九年一贯制学校"},{"name":"中山市君里学校","address":"广东省中山市三乡镇环镇路27号","phone":"760-86323632","code":" 3144002488","nature":"初级中学"},{"name":"中山市三乡南峰学校","address":"广东省中山市三乡镇南龙村聚龙路10号","phone":"760-86683967","code":" 3144002489","nature":"九年一贯制学校"},{"name":"中山市板芙镇板芙初级中学","address":"中山市板芙镇板尾村河西东路219号","phone":"760-86501465","code":" 3144002490","nature":"初级中学"},{"name":"中山市板芙镇第一中学","address":"广东省中山市板芙镇湖洲村四街41号","phone":"760-86508402","code":" 3144002491","nature":"初级中学"},{"name":"中山市板芙芙蓉学校","address":"广东省中山市板芙镇置业路8号","phone":"760-86512069","code":" 3144002492","nature":"九年一贯制学校"},{"name":"中山市同方学校","address":"广东省中山市板芙镇白溪村沙浦街","phone":"760-86505158","code":" 3144002493","nature":"九年一贯制学校"},{"name":"中山市卓山中学","address":"广东省中山市大涌镇中新公路163号","phone":"760-87122307","code":" 3144002494","nature":"初级中学"},{"name":"中山市大涌旗风学校","address":"广东省中山市大涌镇石井村","phone":"760-87770808","code":" 3144002495","nature":"九年一贯制学校"},{"name":"中山市神湾镇神湾中学","address":"广东省中山市神湾镇敬业路1号","phone":"760-86609214","code":" 3144002496","nature":"初级中学"},{"name":"中山市神湾神舟学校","address":"广东省中山市神湾镇外沙村民委员会","phone":"760-86606178","code":" 3144002497","nature":"九年一贯制学校"},{"name":"中山市神湾育才学校","address":"广东省中山市神湾镇海港村西环街67号","phone":"760-86606038","code":" 3144002498","nature":"九年一贯制学校"},{"name":"中山市建勋中学","address":"广东省中山市石岐区民权路23号","phone":"760-88829125","code":" 3144002499","nature":"九年一贯制学校"},{"name":"中山市南朗旗风学校","address":"广东省中山市南朗镇正街1号","phone":"760-86627058","code":" 3144003198","nature":"九年一贯制学校"},{"name":"中山市纪雅学校","address":"广东省中山市火炬高技术产业开发区凯茵新城憧憬路15号","phone":"760-88337801","code":" 3144003347","nature":"初级中学"},{"name":"中山市民众中学","address":"广东省中山市民众街道民众大道113号","phone":"760-85571830","code":" 3144003361","nature":"初级中学"},{"name":"中山火炬高技术产业开发区第二中学","address":"中山市火炬开发区环茂二路黎村","phone":"760-88299791","code":" 3144003533","nature":"初级中学"},{"name":"中山市西区铁城初级中学","address":"西区翠景道（南）17号地块之28","phone":"760-88633276","code":" 3144003757","nature":"初级中学"},{"name":"中山市神湾镇崇正学校","address":"中山市神湾镇外沙村天熹路8号","phone":"760-86609860","code":" 3144003955","nature":"九年一贯制学校"},{"name":"中山市横栏伟智学校","address":"中山市横栏镇南苑路三巷1号","phone":"760-87680882","code":" 3144004054","nature":"九年一贯制学校"},{"name":"中山市东凤镇梅沙实验学校","address":"","phone":"760-89997966","code":" 3144004064","nature":"九年一贯制学校"},{"name":"中山市五桂山学校","address":"广东省中山市五桂山区石鼓居委会商业街110号","phone":"760-88209385","code":" 3144089471","nature":"九年一贯制学校"},{"name":"中山市东区艳阳学校","address":"广东省中山市东区大熬溪村永丰街4号","phone":"760-88329941","code":" 3144089472","nature":"九年一贯制学校"},{"name":"中山市卓雅学校","address":"广东省中山市火炬开发区东镇东一路25号","phone":"760-28210376","code":" 3444000682","nature":"九年一贯制学校"},{"name":"中山市横栏中学","address":"中山市横栏镇顺兴北路8号","phone":"760-87766519","code":" 3444000692","nature":"初级中学"},{"name":"中山市阳光学校","address":"","phone":"760-88916826","code":" 3744000016","nature":"专门学校"}]